aibaba_ai_text_splitters/__init__.py
aibaba_ai_text_splitters/base.py
aibaba_ai_text_splitters/character.py
aibaba_ai_text_splitters/html.py
aibaba_ai_text_splitters/json.py
aibaba_ai_text_splitters/konlpy.py
aibaba_ai_text_splitters/latex.py
aibaba_ai_text_splitters/markdown.py
aibaba_ai_text_splitters/nltk.py
aibaba_ai_text_splitters/py.typed
aibaba_ai_text_splitters/python.py
aibaba_ai_text_splitters/sentence_transformers.py
aibaba_ai_text_splitters/spacy.py
aibaba_ai_text_splitters/xsl/converting_to_header.xslt
aibaba_ai_text_splitters/xsl/html_chunks_with_headers.xslt
aibaba_ai_text_splitters-0.3.6.dist-info/METADATA
aibaba_ai_text_splitters-0.3.6.dist-info/WHEEL
aibaba_ai_text_splitters-0.3.6.dist-info/RECORD
