Metadata-Version: 2.1
Name: aibaba_ai_text_splitters
Version: 0.3.6
Summary: Aibaba AI text splitting utilities
Home-page: https://github.com/aibaba-ai/aibaba-ai
License: MIT
Requires-Python: >=3.9,<4.0
Classifier: License :: OSI Approved :: MIT License
Classifier: Programming Language :: Python :: 3
Classifier: Programming Language :: Python :: 3.9
Classifier: Programming Language :: Python :: 3.10
Classifier: Programming Language :: Python :: 3.11
Classifier: Programming Language :: Python :: 3.12
Requires-Dist: aibaba-ai-core (>=0.3.29,<0.4.0)
Project-URL: Repository, https://github.com/aibaba-ai/aibaba-ai
Project-URL: Release Notes, https://github.com/aibaba-ai/aibaba-ai/releases?q=tag%3A%22aibaba_ai_text_splitters%3D%3D0%22&expanded=true
Project-URL: Source Code, https://github.com/aibaba-ai/aibaba-ai/tree/master/libs/text-splitters
